bib4llm/__init__.py
bib4llm/cli.py
bib4llm/process_bibliography.py
bib4llm/watcher.py
bib4llm-0.2.2.dist-info/METADATA
bib4llm-0.2.2.dist-info/WHEEL
bib4llm-0.2.2.dist-info/entry_points.txt
bib4llm-0.2.2.dist-info/licenses/LICENSE
bib4llm-0.2.2.dist-info/RECORD
