Metadata-Version: 2.4
Name: bib4llm
Version: 0.2.2
Summary: Extract text and figures from BibTeX library attachments into LLM-readable formats for AI-assisted research
Project-URL: Homepage, https://github.com/denisalevi/bib4llm
Project-URL: Bug Tracker, https://github.com/denisalevi/bib4llm/issues
Author: Denis Alevi
License-File: LICENSE
Classifier: Development Status :: 3 - Alpha
Classifier: Intended Audience :: Science/Research
Classifier: License :: OSI Approved :: GNU General Public License v3 (GPLv3)
Classifier: Operating System :: OS Independent
Classifier: Programming Language :: Python :: 3
Classifier: Topic :: Scientific/Engineering :: Artificial Intelligence
Classifier: Topic :: Text Processing :: Markup
Requires-Python: >=3.6
Requires-Dist: bibtexparser
Requires-Dist: pymupdf4llm
Requires-Dist: tqdm
Requires-Dist: watchdog
Provides-Extra: test
Requires-Dist: pytest; extra == 'test'
Requires-Dist: pytest-cov; extra == 'test'
Requires-Dist: pytest-xdist; extra == 'test'
